airflow_provider_hightouch/__init__.py
airflow_provider_hightouch/consts.py
airflow_provider_hightouch/types.py
airflow_provider_hightouch/utils.py
airflow_provider_hightouch/version.py
airflow_provider_hightouch/example_dags/__init__.py
airflow_provider_hightouch/example_dags/example_hightouch_trigger_sync.py
airflow_provider_hightouch/hooks/__init__.py
airflow_provider_hightouch/hooks/hightouch.py
airflow_provider_hightouch/operators/__init__.py
airflow_provider_hightouch/operators/hightouch.py
airflow_provider_hightouch/sensors/__init__.py
airflow_provider_hightouch/sensors/hightouch.py
tests/__init__.py
tests/hooks/__init__.py
tests/hooks/test_hightouch_hook.py
tests/operators/__init__.py
tests/operators/test_hightouch_operator.py
airflow_provider_hightouch-4.0.0.dist-info/LICENSE
airflow_provider_hightouch-4.0.0.dist-info/METADATA
airflow_provider_hightouch-4.0.0.dist-info/WHEEL
airflow_provider_hightouch-4.0.0.dist-info/entry_points.txt
airflow_provider_hightouch-4.0.0.dist-info/top_level.txt
airflow_provider_hightouch-4.0.0.dist-info/RECORD
