Metadata-Version: 2.1
Name: airflow-provider-hightouch
Version: 4.0.0
Summary: Hightouch Provider for Airflow
Home-page: https://github.com/hightouchio/airflow-provider-hightouch
Author: Hightouch
Author-email: pedram@hightouch.io
License: Apache License 2.0
Project-URL: Bug Tracker, https://github.com/hightouchio/airflow-provider-hightouch/issues
Classifier: Development Status :: 4 - Beta
Classifier: License :: OSI Approved :: Apache Software License
Classifier: Programming Language :: Python :: 3
Classifier: Operating System :: OS Independent
Requires-Python: >=3.6
License-File: LICENSE
Requires-Dist: requests
Requires-Dist: apache-airflow (>=1.10)
